Metadata-Version: 1.0
Name: distribution-sp-01
Version: 11.0
Summary: Gaussian & Binomial distributions
Home-page: UNKNOWN
Author: Sandeep
Author-email: UNKNOWN
License: UNKNOWN
Platform: UNKNOWN
